{"version": "1", "message": "ERROR: Hidden Testcases server unreachable.", "problem_id": "ads2_m10_a1_1", "user_id": "Arepallyrakesh", "score": {"sample": {"0": {"execution_time": 0.6882333755493164, "passed": true}, "1": {"execution_time": 0.8047735691070557, "passed": true}, "2": {"execution_time": 0.5215790271759033, "passed": true}, "3": {"execution_time": 0.18226838111877441, "passed": true}, "4": {"execution_time": 0.6263823509216309, "passed": true}, "5": {"execution_time": 0.6742289066314697, "passed": true}, "6": {"execution_time": 6.440206050872803, "passed": true}, "7": {"execution_time": 0.47201108932495117, "passed": true}, "8": {"execution_time": 7.0755980014801025, "passed": true}}}, "check_style_score": "1/1"}